CHANGES.txt
README.txt
setup.py
benchmaster/__init__.py
benchmaster/master.py
benchmaster/node.py
benchmaster/utils.py
benchmaster.egg-info/PKG-INFO
benchmaster.egg-info/SOURCES.txt
benchmaster.egg-info/dependency_links.txt
benchmaster.egg-info/entry_points.txt
benchmaster.egg-info/not-zip-safe
benchmaster.egg-info/requires.txt
benchmaster.egg-info/top_level.txt