Metadata-Version: 1.0
Name: benchmaster
Version: 1.0b1
Summary: Tools for running and automating distributed loadtests with Funkload
Home-page: http://pypi.python.org/pypi/funkload-bench
Author: Julian Coyne and Martin Aspeli
Author-email: optilude@gmail.com
License: GPL2
Keywords: funkload clustered load testing
Platform: UNKNOWN
